odoo10_addon_disable_odoo_online-10.0.1.0.0-py2.7-nspkg.pth
odoo10_addon_disable_odoo_online-10.0.1.0.0.dist-info/top_level.txt
odoo10_addon_disable_odoo_online-10.0.1.0.0.dist-info/WHEEL
odoo10_addon_disable_odoo_online-10.0.1.0.0.dist-info/RECORD
odoo10_addon_disable_odoo_online-10.0.1.0.0.dist-info/metadata.json
odoo10_addon_disable_odoo_online-10.0.1.0.0.dist-info/DESCRIPTION.rst
odoo10_addon_disable_odoo_online-10.0.1.0.0.dist-info/METADATA
odoo10_addon_disable_odoo_online-10.0.1.0.0.dist-info/namespace_packages.txt
odoo/addons/disable_odoo_online/__manifest__.py
odoo/addons/disable_odoo_online/__init__.py
odoo/addons/disable_odoo_online/README.rst
odoo/addons/disable_odoo_online/models/publisher_warranty_contract.py
odoo/addons/disable_odoo_online/models/__init__.py
odoo/addons/disable_odoo_online/i18n/es.po
odoo/addons/disable_odoo_online/i18n/hr.po
odoo/addons/disable_odoo_online/i18n/sl.po
odoo/addons/disable_odoo_online/i18n/de.po
odoo/addons/disable_odoo_online/i18n/fr.po
odoo/addons/disable_odoo_online/i18n/pt_BR.po
odoo/addons/disable_odoo_online/i18n/hr_HR.po
odoo/addons/disable_odoo_online/views/ir_ui_menu.xml
odoo/addons/disable_odoo_online/data/ir_cron.xml
odoo/addons/disable_odoo_online/static/description/icon.png
odoo/addons/disable_odoo_online/static/src/xml/base.xml
